odoo/addons/account_invoice_supplier_ref_reuse/README.rst
odoo/addons/account_invoice_supplier_ref_reuse/__init__.py
odoo/addons/account_invoice_supplier_ref_reuse/__manifest__.py
odoo/addons/account_invoice_supplier_ref_reuse/models/__init__.py
odoo/addons/account_invoice_supplier_ref_reuse/models/account_invoice.py
odoo/addons/account_invoice_supplier_ref_reuse/tests/__init__.py
odoo/addons/account_invoice_supplier_ref_reuse/tests/test_invoice_supplier_reference_reuse.py
odoo11_addon_account_invoice_supplier_ref_reuse-11.0.1.0.0.dist-info/DESCRIPTION.rst
odoo11_addon_account_invoice_supplier_ref_reuse-11.0.1.0.0.dist-info/METADATA
odoo11_addon_account_invoice_supplier_ref_reuse-11.0.1.0.0.dist-info/RECORD
odoo11_addon_account_invoice_supplier_ref_reuse-11.0.1.0.0.dist-info/WHEEL
odoo11_addon_account_invoice_supplier_ref_reuse-11.0.1.0.0.dist-info/metadata.json
odoo11_addon_account_invoice_supplier_ref_reuse-11.0.1.0.0.dist-info/top_level.txt
